examples/__init__.py
examples/crud.py
examples/serve-braids.py
examples/wsgi.py
gink/__init__.py
gink/__main__.py
gink/py.typed
gink/builders/__init__.py
gink/builders/behavior_pb2.py
gink/builders/bundle_pb2.py
gink/builders/change_pb2.py
gink/builders/claim_pb2.py
gink/builders/clearance_pb2.py
gink/builders/container_pb2.py
gink/builders/entry_pb2.py
gink/builders/key_pair_pb2.py
gink/builders/key_pb2.py
gink/builders/log_file_pb2.py
gink/builders/movement_pb2.py
gink/builders/muid_pb2.py
gink/builders/pair_pb2.py
gink/builders/sync_message_pb2.py
gink/builders/value_pb2.py
gink/impl/__init__.py
gink/impl/abstract_store.py
gink/impl/accumulator.py
gink/impl/addressable.py
gink/impl/attribution.py
gink/impl/bound_bundler.py
gink/impl/box.py
gink/impl/braid.py
gink/impl/braid_server.py
gink/impl/builders.py
gink/impl/bundle_info.py
gink/impl/bundle_store.py
gink/impl/bundler.py
gink/impl/coding.py
gink/impl/connection.py
gink/impl/container.py
gink/impl/database.py
gink/impl/decomposition.py
gink/impl/directory.py
gink/impl/dummy.py
gink/impl/get_container.py
gink/impl/graph.py
gink/impl/group.py
gink/impl/has_map.py
gink/impl/key_set.py
gink/impl/listener.py
gink/impl/lmdb_store.py
gink/impl/lmdb_utilities.py
gink/impl/log_backed_store.py
gink/impl/looping.py
gink/impl/memory_store.py
gink/impl/muid.py
gink/impl/pair_map.py
gink/impl/pair_set.py
gink/impl/property.py
gink/impl/relay.py
gink/impl/selectable_console.py
gink/impl/sequence.py
gink/impl/server.py
gink/impl/sync_func.py
gink/impl/timing.py
gink/impl/tuples.py
gink/impl/typedefs.py
gink/impl/utilities.py
gink/impl/watcher.py
gink/impl/wsgi_listener.py
gink/tests/__init__.py
gink/tests/__main__.py
gink/tests/test_accumulator.py
gink/tests/test_box.py
gink/tests/test_braid.py
gink/tests/test_braid_server.py
gink/tests/test_chain_tracker.py
gink/tests/test_change_set_info.py
gink/tests/test_code_values.py
gink/tests/test_connection.py
gink/tests/test_database.py
gink/tests/test_demo.py
gink-0.20260115.1768439183.dist-info/licenses/LICENSE
gink-0.20260115.1768439183.dist-info/METADATA
gink-0.20260115.1768439183.dist-info/WHEEL
gink-0.20260115.1768439183.dist-info/top_level.txt
gink-0.20260115.1768439183.dist-info/RECORD
