Metadata-Version: 2.4
Name: gink
Version: 0.20260115.1768439183
Summary: a system for storing data structures in lmdb
Home-page: https://github.com/x5e/gink
Author: Darin McGill
Author-email: gink@darinmcgill.com
Keywords: gink lmdb crdt history versioned
Classifier: Development Status :: 4 - Beta
Classifier: Intended Audience :: Developers
Classifier: Programming Language :: Python :: 3
Classifier: Programming Language :: Python :: 3.12
Classifier: License :: OSI Approved :: Apache Software License
Requires-Python: >=3.12, <4
License-File: LICENSE
Requires-Dist: wsproto
Requires-Dist: sortedcontainers
Requires-Dist: lmdb
Requires-Dist: protobuf
Requires-Dist: psutil
Requires-Dist: authlib
Requires-Dist: typeguard
Requires-Dist: pynacl
Requires-Dist: python-dateutil
Requires-Dist: typing-extensions
Requires-Dist: requests
Provides-Extra: test
Requires-Dist: nose2; extra == "test"
Requires-Dist: flask; extra == "test"
Provides-Extra: lint
Requires-Dist: mypy; extra == "lint"
Provides-Extra: performance
Requires-Dist: matplotlib; extra == "performance"
Provides-Extra: docs
Requires-Dist: sphinx; extra == "docs"
Requires-Dist: myst-parser; extra == "docs"
Requires-Dist: sphinx-rtd-theme; extra == "docs"
Requires-Dist: sphinx-copybutton; extra == "docs"
Dynamic: author
Dynamic: author-email
Dynamic: classifier
Dynamic: description
Dynamic: description-content-type
Dynamic: home-page
Dynamic: keywords
Dynamic: license-file
Dynamic: provides-extra
Dynamic: requires-dist
Dynamic: requires-python
Dynamic: summary
